{
  "date": "2025-03-14",
  "count": 1,
  "data": [
    {
      "id": "19b3b540",
      "title": "谷歌Gemini 2.0 Flash全模态图像生成上线，动嘴就能P图",
      "content": "谷歌Gemini 2.0 Flash全模态图像生成功能正式上线，用户可通过自然语言对话生成和编辑图像，支持文本与图像结合、对话式编辑、世界知识理解和文本渲染等亮点。开发者可通过Gemini API或Google AI Studio使用。",
      "originalContent": "谷歌Gemini 2.0 Flash全模态图像生成上线，动嘴就能P图 谷歌Gemini 2.0 Flash全模态图像生成功能正式上线，用户可通过自然语言对话生成和编辑图像，支持文本与图像结合、对话式编辑、世界知识理解和文本渲染等亮点。开发者可通过Gemini API或Google AI Studio使用。",
      "source": "AI工具集",
      "sourceUrl": "https://ai-bot.cn/daily-ai-news/",
      "publishTime": "2025-03-14T00:00:00.000Z",
      "crawlTime": "2025-07-15T16:22:19.693Z",
      "category": "产品发布",
      "tags": [
        "发布",
        "AI工具"
      ],
      "dateText": "3月14日·周五"
    }
  ],
  "updateTime": "2025-07-15T16:22:19.889Z"
}